{
	"info": {
		"_postman_id": "6d4c4e1d-6a6f-498b-8d1b-c4fc5ae0c03b",
		"name": "SoporteEstudiantil",
		"schema": "https://schema.getpostman.com/json/collection/v2.1.0/collection.json",
		"_exporter_id": "39548337"
	},
	"item": [
		{
			"name": "http://localhost:8080/api/tickets",
			"protocolProfileBehavior": {
				"disableBodyPruning": true
			},
			"request": {
				"method": "GET",
				"header": [],
				"body": {
					"mode": "raw",
					"raw": "{\r\n  \"contenido\": \"Usa el metodo de Fermant\"\r\n}\r\n",
					"options": {
						"raw": {
							"language": "json"
						}
					}
				},
				"url": {
					"raw": "http://localhost:8080/api/tickets",
					"protocol": "http",
					"host": [
						"localhost"
					],
					"port": "8080",
					"path": [
						"api",
						"tickets"
					]
				}
			},
			"response": []
		},
		{
			"name": "http://localhost:8080/api/tickets\n",
			"protocolProfileBehavior": {
				"disableBodyPruning": true
			},
			"request": {
				"method": "GET",
				"header": [],
				"body": {
					"mode": "raw",
					"raw": "{\r\n  \"contenido\": \"Usa el metodo de Fermant\"\r\n}\r\n",
					"options": {
						"raw": {
							"language": "json"
						}
					}
				},
				"url": {
					"raw": "http://localhost:8080/api/tickets\n",
					"protocol": "http",
					"host": [
						"localhost"
					],
					"port": "8080",
					"path": [
						"api",
						"tickets\n"
					]
				}
			},
			"response": []
		},
		{
			"name": "http://localhost:8080/api/tickets/2/respuestas",
			"request": {
				"method": "POST",
				"header": [],
				"body": {
					"mode": "raw",
					"raw": "{\r\n  \"contenido\": \"Usa el metodo de Fermant\"\r\n}\r\n",
					"options": {
						"raw": {
							"language": "json"
						}
					}
				},
				"url": {
					"raw": "http://localhost:8080/api/tickets/2/respuestas",
					"protocol": "http",
					"host": [
						"localhost"
					],
					"port": "8080",
					"path": [
						"api",
						"tickets",
						"2",
						"respuestas"
					]
				}
			},
			"response": []
		},
		{
			"name": "http://localhost:8080/api/tickets",
			"protocolProfileBehavior": {
				"disableBodyPruning": true
			},
			"request": {
				"method": "GET",
				"header": [],
				"body": {
					"mode": "raw",
					"raw": "{\r\n  \"titulo\": \"¿Cómo mejorar mis habilidades de programación?\",\r\n  \"descripcion\": \"Quiero aprender a escribir mejor código en Kotlin. ¿Alguien tiene recomendaciones?\"\r\n}",
					"options": {
						"raw": {
							"language": "json"
						}
					}
				},
				"url": {
					"raw": "http://localhost:8080/api/tickets",
					"protocol": "http",
					"host": [
						"localhost"
					],
					"port": "8080",
					"path": [
						"api",
						"tickets"
					]
				}
			},
			"response": []
		},
		{
			"name": "http://localhost:8080/api/tickets",
			"request": {
				"method": "POST",
				"header": [],
				"body": {
					"mode": "raw",
					"raw": "{\r\n  \"titulo\": \"¿Cómo mejorar mis habilidades de programación?\",\r\n  \"descripcion\": \"Quiero aprender a escribir mejor código en Kotlin. ¿Alguien tiene recomendaciones?\"\r\n}",
					"options": {
						"raw": {
							"language": "json"
						}
					}
				},
				"url": {
					"raw": "http://localhost:8080/api/tickets",
					"protocol": "http",
					"host": [
						"localhost"
					],
					"port": "8080",
					"path": [
						"api",
						"tickets"
					]
				}
			},
			"response": []
		},
		{
			"name": "http://localhost:8080/api/tickets",
			"protocolProfileBehavior": {
				"disableBodyPruning": true
			},
			"request": {
				"method": "GET",
				"header": [],
				"body": {
					"mode": "raw",
					"raw": "{\r\n  \"contenido\": \"Puedes usar la fórmula general.\"\r\n}",
					"options": {
						"raw": {
							"language": "json"
						}
					}
				},
				"url": {
					"raw": "http://localhost:8080/api/tickets",
					"protocol": "http",
					"host": [
						"localhost"
					],
					"port": "8080",
					"path": [
						"api",
						"tickets"
					]
				}
			},
			"response": []
		},
		{
			"name": "http://localhost:8080/api/tickets/2/respuestas",
			"request": {
				"method": "POST",
				"header": [],
				"body": {
					"mode": "raw",
					"raw": "{\r\n  \"contenido\": \"Puedes usar la fórmula general.\"\r\n}",
					"options": {
						"raw": {
							"language": "json"
						}
					}
				},
				"url": {
					"raw": "http://localhost:8080/api/tickets/2/respuestas",
					"protocol": "http",
					"host": [
						"localhost"
					],
					"port": "8080",
					"path": [
						"api",
						"tickets",
						"2",
						"respuestas"
					]
				}
			},
			"response": []
		},
		{
			"name": "http://localhost:8080/api/tickets",
			"protocolProfileBehavior": {
				"disableBodyPruning": true
			},
			"request": {
				"method": "GET",
				"header": [],
				"body": {
					"mode": "raw",
					"raw": "{\r\n  \"contenido\": \"Puedes usar la fórmula general.\"\r\n}",
					"options": {
						"raw": {
							"language": "json"
						}
					}
				},
				"url": {
					"raw": "http://localhost:8080/api/tickets",
					"protocol": "http",
					"host": [
						"localhost"
					],
					"port": "8080",
					"path": [
						"api",
						"tickets"
					]
				}
			},
			"response": []
		},
		{
			"name": "http://localhost:8080/api/tickets",
			"request": {
				"method": "POST",
				"header": [],
				"body": {
					"mode": "raw",
					"raw": "{\r\n  \"titulo\": \"¿Cómo resolver este problema de álgebra?\",\r\n  \"descripcion\": \"Necesito ayuda con una ecuación cuadrática.\"\r\n}",
					"options": {
						"raw": {
							"language": "json"
						}
					}
				},
				"url": {
					"raw": "http://localhost:8080/api/tickets",
					"protocol": "http",
					"host": [
						"localhost"
					],
					"port": "8080",
					"path": [
						"api",
						"tickets"
					]
				}
			},
			"response": []
		}
	]
}